mazerango/__init__.py
mazerango/asgi.py
mazerango/settings.py
mazerango/urls.py
mazerango/wsgi.py
mazerango-0.1.0.dist-info/LICENSE
mazerango-0.1.0.dist-info/METADATA
mazerango-0.1.0.dist-info/WHEEL
mazerango-0.1.0.dist-info/RECORD
